README.md
setup.py
Topsis_Satyam_101803324.egg-info/PKG-INFO
Topsis_Satyam_101803324.egg-info/SOURCES.txt
Topsis_Satyam_101803324.egg-info/dependency_links.txt
Topsis_Satyam_101803324.egg-info/entry_points.txt
Topsis_Satyam_101803324.egg-info/requires.txt
Topsis_Satyam_101803324.egg-info/top_level.txt
source/__init__.py
source/main.py