Metadata-Version: 2.1
Name: Topsis-Satyam-101803324
Version: 1.0.3
Summary: This package can be used to calculate the topsis score of multiple component data and rank them accordingly
Home-page: https://pypi.org/project/Topsis-Satyam-101803324
Author: Satyam Verma
Author-email: satyamv069@gmail.com
License: MIT
Keywords: TOPSIS
Platform: UNKNOWN
Classifier: Programming Language :: Python :: 3
Classifier: License :: OSI Approved :: MIT License
Classifier: Operating System :: OS Independent
Classifier: Programming Language :: Python :: 3
Classifier: Programming Language :: Python :: 3.4
Classifier: Programming Language :: Python :: 3.5
Classifier: Programming Language :: Python :: 3.6
